eanalytics_api_py/__init__.py
eanalytics_api_py/conn/__init__.py
eanalytics_api_py/conn/_download_datamining.py
eanalytics_api_py/conn/_download_edw.py
eanalytics_api_py/conn/_download_flat_overview_realtime_report.py
eanalytics_api_py/conn/_download_flat_realtime_report.py
eanalytics_api_py/conn/_download_realtime_report.py
eanalytics_api_py/eajupyter/__init__.py
eanalytics_api_py/eajupyter/html.py
eanalytics_api_py/eajupyter/widget.py
eanalytics_api_py/eaload/__init__.py
eanalytics_api_py/eaload/datamining.py
eanalytics_api_py/eaload/generic.py
eanalytics_api_py/earequest/__init__.py
eanalytics_api_py/earequest/datamining/__init__.py
eanalytics_api_py/earequest/datamining/payload.py
eanalytics_api_py/eatransform/__init__.py
eanalytics_api_py/eatransform/pddf.py
eanalytics_api_py/internal/__init__.py
eanalytics_api_py/internal/_log.py
eanalytics_api_py/internal/_os.py
eanalytics_api_py/internal/_request.py
eanalytics_api_py/internal/realtime_overview/__init__.py
eanalytics_api_py/internal/realtime_overview/path/__init__.py
eanalytics_api_py/internal/realtime_overview/path/_insummary.py
eanalytics_api_py-0.1.51.dist-info/licenses/LICENSE
eanalytics_api_py-0.1.51.dist-info/METADATA
eanalytics_api_py-0.1.51.dist-info/WHEEL
eanalytics_api_py-0.1.51.dist-info/top_level.txt
eanalytics_api_py-0.1.51.dist-info/RECORD
