Metadata-Version: 2.4
Name: eanalytics_api_py
Version: 0.1.51
Summary: Locally download a datamining dataset from the Eulerian Technologies API
Home-page: https://github.com/EulerianTechnologies/eanalytics-api-py
Download-URL: https://github.com/EulerianTechnologies/eanalytics-api-py/archive/master.zip
Author: Florian
Author-email: f.dauphin@eulerian.com
Keywords: eulerian,datamining,download,dw,data warehouse,eanalytics,jupyter,notebook,data science
Platform: any
Classifier: Programming Language :: Python :: 3
Classifier: License :: OSI Approved :: GNU General Public License v3 or later (GPLv3+)
Classifier: Operating System :: OS Independent
Requires-Python: >=3.6
License-File: LICENSE
Requires-Dist: requests>=2.23.0
Requires-Dist: ijson>=3.0.4
Requires-Dist: pandas>=1.0.3
Requires-Dist: ipython>=7.16.1
Requires-Dist: ipywidgets>=7.5.1
Requires-Dist: numpy>=1.19.1
Requires-Dist: pytest>=6.1.1
Requires-Dist: pathlib>=1.0.1
Dynamic: author
Dynamic: author-email
Dynamic: classifier
Dynamic: description
Dynamic: description-content-type
Dynamic: download-url
Dynamic: home-page
Dynamic: keywords
Dynamic: license-file
Dynamic: platform
Dynamic: requires-dist
Dynamic: requires-python
Dynamic: summary
